MANIFEST.in
setup.py
version
message_api/__init__.py
message_api/channel.py
message_api.egg-info/PKG-INFO
message_api.egg-info/SOURCES.txt
message_api.egg-info/dependency_links.txt
message_api.egg-info/requires.txt
message_api.egg-info/top_level.txt