Metadata-Version: 1.0
Name: message-api
Version: 1.0.1
Summary: Message API
Home-page: https://github.com/message-api/message-api-python
Author: UNKNOWN
Author-email: UNKNOWN
License: UNKNOWN
Keywords: channel,api,message
Platform: UNKNOWN
